<?xml version="1.0" encoding="UTF-8" ?>
<events>
	<event type="test" name="Test Istorie" day="11" month="10">Test la istorie. 
		Despre tot ce am facut pana acum.
	</event>
	<event type="test" name="Test Mate" day="15" month="10">Test la mate. 
		Din integrale.
	</event>
	<event type="test" name="Test Biologie" day="22" month="10">Test la biologie. 
		Inarmati-va cu rabdare!
	</event>
	<event type="teza" name="Teza Chimie" day="27" month="11">Teza chimie. 
		V-om pune niste note!
	</event>
	<event type="event" name="Poze Jigovan" day="25" month="10">Vor fi 2 sedinte foto. 
		Prima se va desfasura la Teba, iar cealalta la Ceala.
	</event>
</events>